ckmutil/__init__.py
ckmutil/ckm.py
ckmutil/diag.py
ckmutil/phases.py
ckmutil/test_ckm.py
ckmutil/test_diag.py
ckmutil/test_phases.py
ckmutil-1.2.0.dist-info/LICENSE.txt
ckmutil-1.2.0.dist-info/METADATA
ckmutil-1.2.0.dist-info/WHEEL
ckmutil-1.2.0.dist-info/top_level.txt
ckmutil-1.2.0.dist-info/RECORD
