Metadata-Version: 2.1
Name: ckmutil
Version: 1.2.0
Summary: Useful functions for dealing with quark and lepton mixing matrices.
Author-email: "David M. Straub" <straub@protonmail.com>
License: MIT
Project-URL: Homepage, https://davidmstraub.github.io/ckmutil
License-File: LICENSE.txt
Requires-Dist: numpy >=1.20
Requires-Dist: scipy
